{
  "Make": "Alpina",
  "Models": [
    {
      "Model": "B10",
      "Generations": [
        "01.1997 - 05.2004  3 поколение",
        "01.1997 - 05.2004  3 поколение",
        "04.1993 - 05.1996  2 поколение",
        "04.1988 - 05.1996  2 поколение",
        "07.1985 - 12.1987  1 поколение"
      ]
    },
    {
      "Model": "B11",
      "Generations": [
        "01.1987 - 12.1993  1 поколение"
      ]
    },
    {
      "Model": "B12",
      "Generations": [
        "12.1995 - 07.2001  3 поколение",
        "06.1990 - 12.1996  2 поколение",
        "07.1988 - 01.1994  1 поколение"
      ]
    },
    {
      "Model": "B3",
      "Generations": [
        "Р 11.2012 - 06.2017  3 поколение",
        "Р 11.2012 - 06.2017  3 поколение",
        "Р 07.2010 - 10.2012  2 поколение",
        "Р 07.2010 - 10.2012  2 поколение",
        "Р 07.2010 - 10.2012  2 поколение",
        "Р 07.2010 - 10.2012  2 поколение",
        "09.2015 - 05.2019  3 поколение, рестайлинг",
        "09.2015 - 10.2018  3 поколение, рестайлинг"
      ]
    },
    {
      "Model": "B4",
      "Generations": [
        "Р 03.2013 - 06.2017  1 поколение",
        "Р 11.2012 - 06.2017  1 поколение"
      ]
    },
    {
      "Model": "B5",
      "Generations": [
        "09.2020 -  3 поколение, рестайлинг",
        "09.2020 -  3 поколение, рестайлинг",
        "03.2017 - 09.2020  3 поколение",
        "03.2017 - 09.2020  3 поколение",
        "11.2010 - 06.2017  2 поколение",
        "11.2010 - 06.2017  2 поколение",
        "02.2005 - 05.2010  1 поколение",
        "02.2005 - 05.2010  1 поколение"
      ]
    },
    {
      "Model": "B6",
      "Generations": [
        "Р 11.2013 - 06.2017  1 поколение",
        "Р 11.2011 - 06.2017  1 поколение",
        "Р 11.2011 - 06.2017  1 поколение"
      ]
    },
    {
      "Model": "B7",
      "Generations": [
        "Р 11.2009 - 06.2017  3 поколение",
        "04.1984 - 06.1988  2 поколение",
        "12.1978 - 05.1982  1 поколение"
      ]
    },
    {
      "Model": "B8",
      "Generations": [
        "01.1995 - 11.1998  1 поколение",
        "01.1995 - 11.1998  1 поколение"
      ]
    },
    {
      "Model": "B9",
      "Generations": [
        "08.1982 - 12.1985  1 поколение",
        "11.1981 - 12.1985  1 поколение"
      ]
    },
    {
      "Model": "C1",
      "Generations": [
        "08.1983 - 11.1985  2 поколение",
        "04.1980 - 07.1983  1 поколение"
      ]
    },
    {
      "Model": "C2",
      "Generations": [
        "04.1986 - 07.1987  1 поколение",
        "02.1986 - 07.1987  1 поколение"
      ]
    },
    {
      "Model": "D10",
      "Generations": [
        "Р 03.2000 - 11.2003  1 поколение"
      ]
    },
    {
      "Model": "D3",
      "Generations": [
        "Р 03.2013 - 06.2017  2 поколение",
        "Р 03.2013 - 06.2017  2 поколение",
        "07.2008 - 05.2013  1 поколение",
        "12.2005 - 05.2013  1 поколение",
        "12.2005 - 05.2013  1 поколение"
      ]
    },
    {
      "Model": "D4",
      "Generations": [
        "Р 03.2014 - 06.2017  1 поколение",
        "Р 03.2014 - 06.2017  1 поколение"
      ]
    },
    {
      "Model": "D5",
      "Generations": [
        "Р 11.2012 - 06.2017  1 поколение",
        "Р 11.2012 - 06.2017  1 поколение"
      ]
    },
    {
      "Model": "Roadster",
      "Generations": [
        "06.2002 - 10.2003  1 поколение"
      ]
    },
    {
      "Model": "XB7",
      "Generations": [
        "04.2022 -  1 поколение, рестайлинг",
        "05.2020 - 07.2022  1 поколение",
        "04.2022 -  1 поколение, рестайлинг",
        "05.2020 - 07.2022  1 поколение"
      ]
    },
    {
      "Model": "XD3",
      "Generations": [
        "Р 03.2014 - 06.2017  1 поколение, рестайлинг",
        "06.2021 -  2 поколение, рестайлинг",
        "03.2018 - 11.2021  2 поколение",
        "03.2014 - 08.2018  1 поколение, рестайлинг",
        "03.2013 - 03.2014  1 поколение"
      ]
    },
    {
      "Model": "XD4",
      "Generations": [
        "06.2021 -  1 поколение, рестайлинг",
        "03.2018 - 06.2021  1 поколение"
      ]
    }
  ]
}