{
  "Make": "FAW",
  "Models": [
    {
      "Model": "6350",
      "Generations": [
        "Р 01.2005 - 04.2008  1 поколение"
      ]
    },
    {
      "Model": "6371",
      "Generations": [
        "Р 01.2007 - 04.2008  1 поколение"
      ]
    },
    {
      "Model": "Bestune B70",
      "Generations": [
        "Р 04.2020 -  3 поколение",
        "11.2023 -  4 поколение",
        "04.2020 -  3 поколение"
      ]
    },
    {
      "Model": "Bestune B70S",
      "Generations": [
        "11.2021 -  1 поколение"
      ]
    },
    {
      "Model": "Bestune E01",
      "Generations": [
        "09.2020 -  1 поколение"
      ]
    },
    {
      "Model": "Bestune M9",
      "Generations": [
        "11.2022 -  1 поколение, рестайлинг"
      ]
    },
    {
      "Model": "Bestune NAT",
      "Generations": [
        "01.2021 -  1 поколение"
      ]
    },
    {
      "Model": "Bestune T33",
      "Generations": [
        "07.2019 - 11.2021  1 поколение"
      ]
    },
    {
      "Model": "Bestune T55",
      "Generations": [
        "Р 01.2021 -  1 поколение",
        "01.2021 -  1 поколение"
      ]
    },
    {
      "Model": "Bestune T77",
      "Generations": [
        "Р 11.2018 -  1 поколение",
        "12.2022 -  1 поколение, рестайлинг",
        "11.2018 - 11.2022  1 поколение"
      ]
    },
    {
      "Model": "Bestune T90",
      "Generations": [
        "04.2023 -  1 поколение"
      ]
    },
    {
      "Model": "Bestune T99",
      "Generations": [
        "Р 12.2022 -  1 поколение, рестайлинг",
        "12.2022 -  1 поколение, рестайлинг",
        "09.2019 - 12.2022  1 поколение"
      ]
    },
    {
      "Model": "Besturn B30",
      "Generations": [
        "09.2015 - 05.2020  1 поколение"
      ]
    },
    {
      "Model": "Besturn B50",
      "Generations": [
        "Р 06.2012 - 06.2017  1 поколение, рестайлинг",
        "06.2016 - 08.2018  2 поколение"
      ]
    },
    {
      "Model": "Besturn B70",
      "Generations": [
        "Р 08.2013 - 04.2015  1 поколение",
        "05.2014 - 04.2020  2 поколение"
      ]
    },
    {
      "Model": "Besturn X40",
      "Generations": [
        "Р 11.2016 - 01.2022  1 поколение"
      ]
    },
    {
      "Model": "Besturn X40 EV",
      "Generations": [
        "11.2016 -  1 поколение"
      ]
    },
    {
      "Model": "Besturn X80",
      "Generations": [
        "Р 09.2016 - 09.2021  1 поколение, рестайлинг",
        "Р 05.2014 - 09.2019  1 поколение"
      ]
    },
    {
      "Model": "Jinn",
      "Generations": [
        "Р 03.2005 - 11.2009  1 поколение"
      ]
    },
    {
      "Model": "Junpai D60",
      "Generations": [
        "04.2017 - 06.2019  1 поколение, рестайлинг",
        "04.2014 - 03.2017  1 поколение"
      ]
    },
    {
      "Model": "Landmark",
      "Generations": [
        "Р 03.2006 - 11.2009  1 поколение"
      ]
    },
    {
      "Model": "Oley",
      "Generations": [
        "Р 05.2014 - 12.2018  1 поколение"
      ]
    },
    {
      "Model": "Senia R7",
      "Generations": [
        "04.2016 - 11.2019  1 поколение"
      ]
    },
    {
      "Model": "Senia R9",
      "Generations": [
        "04.2018 - 11.2019  1 поколение"
      ]
    },
    {
      "Model": "V2",
      "Generations": [
        "Р 10.2012 - 03.2015  1 поколение"
      ]
    },
    {
      "Model": "V5",
      "Generations": [
        "Р 10.2012 - 06.2017  1 поколение"
      ]
    },
    {
      "Model": "Vita",
      "Generations": [
        "Р 03.2008 - 12.2010  1 поколение",
        "Р 03.2007 - 12.2010  1 поколение"
      ]
    }
  ]
}